{"data":[{"id":"986f66d0-917c-4237-9926-e74ec0503b50","name":"Project mock-1","type":"document","is_temporary":false,"description":"Knowledge base for project mock-1","tenant_id":10002,"chunking_config":{"chunk_size":500,"chunk_overlap":50,"separators":["\n\n","\n","。","！","？"]},"image_processing_config":{"model_id":""},"embedding_model_id":"67743ce2-aead-43a2-ae00-11de9ff0934a","summary_model_id":"63df952e-adca-4642-9fdc-a83117f95973","vlm_config":{"enabled":false,"model_id":"","model_name":"","base_url":"","api_key":"","interface_type":""},"cos_config":{"secret_id":"","secret_key":"","region":"","bucket_name":"","app_id":"","path_prefix":"","provider":""},"extract_config":null,"faq_config":null,"question_generation_config":null,"created_at":"2026-01-20T02:14:17.32065Z","updated_at":"2026-01-20T02:14:17.32065Z","deleted_at":null,"knowledge_count":1,"chunk_count":0,"is_processing":false,"processing_count":0},{"id":"98398725-405a-43c8-96e0-d378f8a52a24","name":"Project mock-1","type":"document","is_temporary":false,"description":"Knowledge base for project mock-1","tenant_id":10002,"chunking_config":{"chunk_size":500,"chunk_overlap":50,"separators":["\n\n","\n","。","！","？"]},"image_processing_config":{"model_id":""},"embedding_model_id":"67743ce2-aead-43a2-ae00-11de9ff0934a","summary_model_id":"63df952e-adca-4642-9fdc-a83117f95973","vlm_config":{"enabled":false,"model_id":"","model_name":"","base_url":"","api_key":"","interface_type":""},"cos_config":{"secret_id":"","secret_key":"","region":"","bucket_name":"","app_id":"","path_prefix":"","provider":""},"extract_config":null,"faq_config":null,"question_generation_config":null,"created_at":"2026-01-20T02:09:49.32135Z","updated_at":"2026-01-20T02:09:49.321351Z","deleted_at":null,"knowledge_count":1,"chunk_count":0,"is_processing":false,"processing_count":0},{"id":"d50f91fa-3171-465d-afe0-86200d98ebd9","name":"Project mock-1","type":"document","is_temporary":false,"description":"Knowledge base for project mock-1","tenant_id":10002,"chunking_config":{"chunk_size":0,"chunk_overlap":0,"separators":null},"image_processing_config":{"model_id":""},"embedding_model_id":"67743ce2-aead-43a2-ae00-11de9ff0934a","summary_model_id":"63df952e-adca-4642-9fdc-a83117f95973","vlm_config":{"enabled":false,"model_id":"","model_name":"","base_url":"","api_key":"","interface_type":""},"cos_config":{"secret_id":"","secret_key":"","region":"","bucket_name":"","app_id":"","path_prefix":"","provider":""},"extract_config":null,"faq_config":null,"question_generation_config":null,"created_at":"2026-01-20T01:58:30.548587Z","updated_at":"2026-01-20T01:58:30.548587Z","deleted_at":null,"knowledge_count":1,"chunk_count":0,"is_processing":false,"processing_count":0}],"success":true}